nexios/__init__.py
nexios/__main__.py
nexios/application.py
nexios/converters.py
nexios/decorator_helper.py
nexios/dependencies.py
nexios/exception_handler.py
nexios/exceptions.py
nexios/logging.py
nexios/pagination.py
nexios/py.typed
nexios/static.py
nexios/status.py
nexios/types.py
nexios/views.py
nexios/_internals/__init__.py
nexios/_internals/_formparsers.py
nexios/_internals/_middleware.py
nexios/_internals/_response_transformer.py
nexios/_internals/_route_builder.py
nexios/auth/__init__.py
nexios/auth/decorator.py
nexios/auth/exceptions.py
nexios/auth/middleware.py
nexios/auth/model.py
nexios/auth/backends/__init__.py
nexios/auth/backends/apikey.py
nexios/auth/backends/base.py
nexios/auth/backends/jwt.py
nexios/auth/backends/session.py
nexios/auth/users/__init__.py
nexios/auth/users/base.py
nexios/auth/users/simple.py
nexios/cli/__init__.py
nexios/cli/main.py
nexios/cli/utils.py
nexios/cli/commands/__init__.py
nexios/cli/commands/new.py
nexios/cli/commands/ping.py
nexios/cli/commands/run.py
nexios/cli/commands/shell.py
nexios/cli/commands/urls.py
nexios/config/__init__.py
nexios/config/base.py
nexios/events/__init__.py
nexios/events/core.py
nexios/events/emitter.py
nexios/events/enums.py
nexios/events/exceptions.py
nexios/events/mixins.py
nexios/events/types.py
nexios/handlers/__init__.py
nexios/handlers/not_found.py
nexios/http/__init__.py
nexios/http/cookies_parser.py
nexios/http/formparsers.py
nexios/http/request.py
nexios/http/response.py
nexios/middleware/__init__.py
nexios/middleware/base.py
nexios/middleware/csrf.py
nexios/middleware/gzip.py
nexios/middleware/security.py
nexios/middleware/utils.py
nexios/middleware/cors/__init__.py
nexios/middleware/cors/_middleware.py
nexios/middleware/cors/config.py
nexios/middleware/errors/__init__.py
nexios/middleware/errors/server_error_handler.py
nexios/objects/__init__.py
nexios/objects/common.py
nexios/objects/datastructures.py
nexios/objects/http.py
nexios/objects/routing.py
nexios/openapi/__init__.py
nexios-3.7.2.dist-info/METADATA
nexios-3.7.2.dist-info/WHEEL
nexios-3.7.2.dist-info/entry_points.txt
nexios-3.7.2.dist-info/licenses/LICENSE
nexios-3.7.2.dist-info/RECORD
