Metadata-Version: 2.4
Name: nexios
Version: 3.7.2
Summary: Nexios is a modern, high-performance ASGI web framework for Python with multi-server support with zero overhead.
Author-email: Chidebele Dunamis <techwithdunamix@gmail.com>
License-Expression: BSD-3-Clause
License-File: LICENSE
Keywords: API,ASGI,HTTP,Python,async,asynchronous,backend,concurrent,framework,granian,real-time,scalable,uvicorn,web,web server,websocket
Requires-Python: >=3.9
Requires-Dist: anyio==4.12.1
Requires-Dist: itsdangerous>=2.1.2
Requires-Dist: pydantic<3.0,>=2.0
Requires-Dist: python-multipart>=0.0.6
Requires-Dist: typing-extensions>=4.12.2; python_version < '3.10'
Requires-Dist: uvicorn>=0.27.0
Provides-Extra: all
Requires-Dist: anyio>=4.0.0; extra == 'all'
Requires-Dist: click>=8.1.3; extra == 'all'
Requires-Dist: granian>=1.2.0; extra == 'all'
Requires-Dist: itsdangerous>=2.1.2; extra == 'all'
Requires-Dist: jinja2>=3.1.6; extra == 'all'
Requires-Dist: pyjwt>=2.7.0; extra == 'all'
Requires-Dist: python-multipart>=0.0.6; extra == 'all'
Requires-Dist: uvicorn>=0.27.0; extra == 'all'
Provides-Extra: cli
Requires-Dist: click>=8.1.3; extra == 'cli'
Provides-Extra: dev
Requires-Dist: anyio>=4.0.0; extra == 'dev'
Requires-Dist: black>=23.0.0; extra == 'dev'
Requires-Dist: click>=8.1.3; extra == 'dev'
Requires-Dist: coverage<8.0,>=6.3; extra == 'dev'
Requires-Dist: httpx<0.29.0,>=0.23.3; extra == 'dev'
Requires-Dist: isort>=5.13.2; extra == 'dev'
Requires-Dist: itsdangerous>=2.1.2; extra == 'dev'
Requires-Dist: jinja2>=3.1.6; extra == 'dev'
Requires-Dist: mypy>=1.15.0; extra == 'dev'
Requires-Dist: pyjwt>=2.7.0; extra == 'dev'
Requires-Dist: pytest-asyncio<1.4.0,>=0.25.3; extra == 'dev'
Requires-Dist: pytest<9.1.0,>=8.3.4; extra == 'dev'
Requires-Dist: python-multipart>=0.0.6; extra == 'dev'
Requires-Dist: ruff>=0.0.256; extra == 'dev'
Requires-Dist: typing-extensions==4.15.0; extra == 'dev'
Requires-Dist: uvicorn>=0.27.0; extra == 'dev'
Provides-Extra: granian
Requires-Dist: granian>=1.2.0; extra == 'granian'
Provides-Extra: http
Requires-Dist: anyio>=4.0.0; extra == 'http'
Requires-Dist: itsdangerous>=2.1.2; extra == 'http'
Requires-Dist: python-multipart>=0.0.6; extra == 'http'
Requires-Dist: uvicorn>=0.27.0; extra == 'http'
Provides-Extra: jwt
Requires-Dist: pyjwt>=2.7.0; extra == 'jwt'
Provides-Extra: templating
Requires-Dist: jinja2>=3.1.6; extra == 'templating'
